odoo/addons/auth_oidc/README.rst
odoo/addons/auth_oidc/__init__.py
odoo/addons/auth_oidc/__manifest__.py
odoo/addons/auth_oidc/controllers/__init__.py
odoo/addons/auth_oidc/controllers/main.py
odoo/addons/auth_oidc/demo/local_keycloak.xml
odoo/addons/auth_oidc/i18n/auth_oidc.pot
odoo/addons/auth_oidc/models/__init__.py
odoo/addons/auth_oidc/models/auth_oauth_provider.py
odoo/addons/auth_oidc/models/res_users.py
odoo/addons/auth_oidc/readme/CONFIGURE.rst
odoo/addons/auth_oidc/readme/CONTRIBUTORS.rst
odoo/addons/auth_oidc/readme/DESCRIPTION.rst
odoo/addons/auth_oidc/readme/HISTORY.rst
odoo/addons/auth_oidc/readme/INSTALL.rst
odoo/addons/auth_oidc/readme/ROADMAP.rst
odoo/addons/auth_oidc/readme/USAGE.rst
odoo/addons/auth_oidc/security/ir.model.access.csv
odoo/addons/auth_oidc/static/description/icon.png
odoo/addons/auth_oidc/static/description/index.html
odoo/addons/auth_oidc/tests/__init__.py
odoo/addons/auth_oidc/tests/test_auth_oidc_auth_code.py
odoo/addons/auth_oidc/tests/keycloak/keycloak-config.json
odoo/addons/auth_oidc/tests/keycloak/keycloak.sh
odoo/addons/auth_oidc/views/auth_oauth_provider.xml
odoo12_addon_auth_oidc-12.0.1.1.0.dist-info/METADATA
odoo12_addon_auth_oidc-12.0.1.1.0.dist-info/WHEEL
odoo12_addon_auth_oidc-12.0.1.1.0.dist-info/top_level.txt
odoo12_addon_auth_oidc-12.0.1.1.0.dist-info/RECORD
