Metadata-Version: 2.1
Name: odoo12-addon-auth-oidc
Version: 12.0.1.1.0
Summary: Allow users to login through OpenID Connect Provider
Home-page: https://github.com/OCA/server-auth
Author: ICTSTUDIO, André Schenkels, ACSONE SA/NV, Odoo Community Association (OCA)
Author-email: support@odoo-community.org
License: AGPL-3
Platform: UNKNOWN
Classifier: Programming Language :: Python
Classifier: Framework :: Odoo
Classifier: Framework :: Odoo :: 12.0
Classifier: License :: OSI Approved :: GNU Affero General Public License v3
Requires-Python: >=3.5
Requires-Dist: odoo (<12.1dev,>=12.0a)
Requires-Dist: python-jose
Requires-Dist: python2-secrets ; python_version < "3.6"
